{
    "cik": "1652044",
    "company": "Alphabet Inc.",
    "filing_type": "8-K",
    "filing_date": "2025-04-24",
    "period_of_report": "2025-04-23",
    "sic": "7370",
    "state_of_inc": "DE",
    "state_location": "CA",
    "fiscal_year_end": "1231",
    "filing_html_index": "https://www.sec.gov/Archives/edgar/data/1652044/0001652044-25-000040-index.html",
    "htm_filing_link": "https://www.sec.gov/Archives/edgar/data/1652044/000165204425000040/goog-20250423.htm",
    "complete_text_filing_link": "https://www.sec.gov/Archives/edgar/data/1652044/0001652044-25-000040.txt",
    "filename": "1652044_8K_2025_0001652044-25-000040.htm",
    "item_1.01": "",
    "item_1.02": "",
    "item_1.03": "",
    "item_1.04": "",
    "item_1.05": "",
    "item_2.01": "",
    "item_2.02": "Item 2.02. Results of Operations and Financial Condition.\nOn April 24, 2025, Alphabet Inc. (“Alphabet” or the “Company”) is issuing a press release and holding a conference call regarding its financial results for the quarter ended March 31, 2025. A copy of the press release is furnished as Exhibit 99.1 to this Current Report on Form 8-K.\nThis information shall not be deemed “filed” for purposes of Section 18 of the Securities Exchange Act of 1934, as amended (the “Exchange Act”), or incorporated by reference in any filing under the Securities Act of 1933, as amended, or the Exchange Act, except as shall be expressly set forth by specific reference in such a filing.\nAlphabet is making reference to non-GAAP financial information in both the press release and the conference call. A reconciliation of these non-GAAP financial measures to the comparable GAAP financial measures is contained in the attached press release.",
    "item_2.03": "",
    "item_2.04": "",
    "item_2.05": "",
    "item_2.06": "",
    "item_3.01": "",
    "item_3.02": "",
    "item_3.03": "",
    "item_4.01": "",
    "item_4.02": "",
    "item_5.01": "",
    "item_5.02": "",
    "item_5.03": "",
    "item_5.04": "",
    "item_5.05": "",
    "item_5.06": "",
    "item_5.07": "",
    "item_5.08": "",
    "item_6.01": "",
    "item_6.02": "",
    "item_6.03": "",
    "item_6.04": "",
    "item_6.05": "",
    "item_7.01": "",
    "item_8.01": "Item 8.01. Other Events.\nOn April 23, 2025, Alphabet’s Board of Directors authorized the Company to repurchase up to an additional $70.0 billion of the Company’s Class A and Class C shares.\nAlphabet’s Board of Directors also declared a quarterly cash dividend of $0.21 payable on June 16, 2025 to stockholders of record for each of the Company’s Class A, Class B, and Class C shares as of June 9, 2025.",
    "item_9.01": "Item 9.01. Financial Statements and Exhibits.\n(d)Exhibits\nExhibit No. Description\n99.1 Press release of Alphabet Inc. dated April 24, 2025\n104 Cover Page Interactive Data File (formatted as inline XBRL)"
}